trackle/__init__.py
trackle/api.py
trackle/context.py
trackle/git.py
trackle/run.py
trackle/storage.py
trackle/utils.py
trackle/cli/__init__.py
trackle/cli/diff_runs.py
trackle/cli/list_runs.py
trackle/cli/main.py
trackle/cli/plot_metrics.py
trackle_ml/__init__.py
trackle_ml/api.py
trackle_ml/context.py
trackle_ml/git.py
trackle_ml/run.py
trackle_ml/storage.py
trackle_ml/utils.py
trackle_ml/cli/__init__.py
trackle_ml/cli/diff_runs.py
trackle_ml/cli/list_runs.py
trackle_ml/cli/main.py
trackle_ml/cli/plot_metrics.py
trackle_ml-0.1.2.dist-info/licenses/LICENSE
trackle_ml-0.1.2.dist-info/METADATA
trackle_ml-0.1.2.dist-info/WHEEL
trackle_ml-0.1.2.dist-info/entry_points.txt
trackle_ml-0.1.2.dist-info/top_level.txt
trackle_ml-0.1.2.dist-info/RECORD
