Metadata-Version: 2.4
Name: trackle-ml
Version: 0.1.2
Summary: Local-first, git-aware ML experiment tracking.
Author: Trackle Developers
License: MIT
Project-URL: Homepage, https://github.com/achintya-p/trackle
Project-URL: Repository, https://github.com/achintya-p/trackle
Keywords: experiment-tracking,mlops,ml,git,local
Classifier: Development Status :: 3 - Alpha
Classifier: Intended Audience :: Developers
Classifier: Intended Audience :: Science/Research
Classifier: License :: OSI Approved :: MIT License
Classifier: Programming Language :: Python :: 3
Classifier: Programming Language :: Python :: 3.9
Classifier: Programming Language :: Python :: 3.10
Classifier: Programming Language :: Python :: 3.11
Classifier: Programming Language :: Python :: 3.12
Classifier: Operating System :: OS Independent
Classifier: Topic :: Scientific/Engineering :: Artificial Intelligence
Classifier: Topic :: Software Development :: Libraries
Requires-Python: >=3.9
License-File: LICENSE
Provides-Extra: viz
Requires-Dist: matplotlib; extra == "viz"
Provides-Extra: rich
Requires-Dist: rich; extra == "rich"
Provides-Extra: dev
Requires-Dist: pytest; extra == "dev"
Requires-Dist: pytest-cov; extra == "dev"
Dynamic: license-file
